MANIFEST.in
README.md
setup.py
oracle_river/__init__.py
oracle_river/author.jpg
oracle_river/oracle_river.py
oracle_river.egg-info/PKG-INFO
oracle_river.egg-info/SOURCES.txt
oracle_river.egg-info/dependency_links.txt
oracle_river.egg-info/entry_points.txt
oracle_river.egg-info/requires.txt
oracle_river.egg-info/top_level.txt