Metadata-Version: 1.1
Name: oracle-river
Version: 0.0.3
Summary: Charger des donnees oracle vers Elasticsearch
Home-page: http://github.com/oneairone/oracle_river
Author: Erwan Gilbert
Author-email: gilberterwan@gmail.com
License: WTFPL
Platform: UNKNOWN
Classifier: Programming Language :: Python
Classifier: Development Status :: 1 - Planning
Classifier: License :: OSI Approved
Classifier: Natural Language :: French
Classifier: Operating System :: OS Independent
Classifier: Programming Language :: Python :: 2.7
Classifier: Topic :: Communications
